{"EnqueuedTimeUtc":"2022-06-25T14:48:57.8290000Z","Properties":{},"SystemProperties":{"connectionDeviceId":"901288002989991","connectionAuthMethod":"{\"scope\":\"device\",\"type\":\"sas\",\"issuer\":\"iothub\",\"acceptingIpFilterRule\":null}","connectionDeviceGenerationId":"637909662877731942","contentType":"application/json","contentEncoding":"utf-8","enqueuedTime":"2022-06-25T14:48:57.8290000Z"},"Body":{"imsi":901288002989991,"sequence":469,"uptime":1688357,"temperature":[{"value":24.71,"timestamp":1656164940000},{"value":24.76,"timestamp":1656165240000},{"value":24.81,"timestamp":1656165540000},{"value":24.89,"timestamp":1656165840000},{"value":24.99,"timestamp":1656166140000},{"value":25.09,"timestamp":1656166440000},{"value":25.18,"timestamp":1656166740000},{"value":25.27,"timestamp":1656167040000},{"value":25.35,"timestamp":1656167340000},{"value":25.4,"timestamp":1656167640000},{"value":25.4,"timestamp":1656167940000},{"value":25.38,"timestamp":1656168240000}],"humidity":[{"value":61,"timestamp":1656164940000},{"value":61,"timestamp":1656165240000},{"value":61,"timestamp":1656165540000},{"value":62,"timestamp":1656165840000},{"value":62,"timestamp":1656166140000},{"value":62,"timestamp":1656166440000},{"value":62,"timestamp":1656166740000},{"value":62,"timestamp":1656167040000},{"value":62,"timestamp":1656167340000},{"value":62,"timestamp":1656167640000},{"value":62,"timestamp":1656167940000},{"value":62,"timestamp":1656168240000}],"orientation":3,"discharged":0,"ecl":1,"signal_power":-88.4,"snr":4.8}}
{"EnqueuedTimeUtc":"2022-06-25T14:50:11.7800000Z","Properties":{},"SystemProperties":{"connectionDeviceId":"901288002989997","connectionAuthMethod":"{\"scope\":\"device\",\"type\":\"sas\",\"issuer\":\"iothub\",\"acceptingIpFilterRule\":null}","connectionDeviceGenerationId":"637909662688020549","contentType":"application/json","contentEncoding":"utf-8","enqueuedTime":"2022-06-25T14:50:11.7800000Z"},"Body":{"imsi":901288002989997,"sequence":465,"uptime":1688428,"temperature":[{"value":24.46,"timestamp":1656165000000},{"value":24.52,"timestamp":1656165300000},{"value":24.63,"timestamp":1656165600000},{"value":24.75,"timestamp":1656165900000},{"value":24.86,"timestamp":1656166200000},{"value":24.98,"timestamp":1656166500000},{"value":25.08,"timestamp":1656166800000},{"value":25.17,"timestamp":1656167100000},{"value":25.24,"timestamp":1656167400000},{"value":25.27,"timestamp":1656167700000},{"value":25.21,"timestamp":1656168000000},{"value":25.17,"timestamp":1656168300000}],"humidity":[{"value":66,"timestamp":1656165000000},{"value":63,"timestamp":1656165300000},{"value":63,"timestamp":1656165600000},{"value":64,"timestamp":1656165900000},{"value":63,"timestamp":1656166200000},{"value":63,"timestamp":1656166500000},{"value":63,"timestamp":1656166800000},{"value":63,"timestamp":1656167100000},{"value":63,"timestamp":1656167400000},{"value":63,"timestamp":1656167700000},{"value":64,"timestamp":1656168000000},{"value":63,"timestamp":1656168300000}],"orientation":3,"discharged":0,"ecl":1,"signal_power":-87.9,"snr":2.9}}