{"EnqueuedTimeUtc":"2022-06-18T23:49:02.3230000Z","Properties":{},"SystemProperties":{"connectionDeviceId":"901288002989991","connectionAuthMethod":"{\"scope\":\"device\",\"type\":\"sas\",\"issuer\":\"iothub\",\"acceptingIpFilterRule\":null}","connectionDeviceGenerationId":"637909662877731942","contentType":"application/json","contentEncoding":"utf-8","enqueuedTime":"2022-06-18T23:49:02.3230000Z"},"Body":{"imsi":901288002989991,"sequence":310,"uptime":1102219,"temperature":[{"value":24.79,"timestamp":1655592540000},{"value":24.8,"timestamp":1655592840000},{"value":24.78,"timestamp":1655593140000},{"value":24.78,"timestamp":1655593440000},{"value":24.78,"timestamp":1655593740000},{"value":24.78,"timestamp":1655594040000},{"value":24.78,"timestamp":1655594340000},{"value":24.77,"timestamp":1655594640000},{"value":24.78,"timestamp":1655594940000},{"value":24.76,"timestamp":1655595240000},{"value":24.77,"timestamp":1655595540000},{"value":24.76,"timestamp":1655595840000}],"humidity":[{"value":45,"timestamp":1655592540000},{"value":45,"timestamp":1655592840000},{"value":45,"timestamp":1655593140000},{"value":45,"timestamp":1655593440000},{"value":45,"timestamp":1655593740000},{"value":45,"timestamp":1655594040000},{"value":45,"timestamp":1655594340000},{"value":45,"timestamp":1655594640000},{"value":45,"timestamp":1655594940000},{"value":45,"timestamp":1655595240000},{"value":45,"timestamp":1655595540000},{"value":45,"timestamp":1655595840000}],"orientation":3,"discharged":0,"ecl":1,"signal_power":-84.2,"snr":4.3}}
{"EnqueuedTimeUtc":"2022-06-18T23:50:09.0960000Z","Properties":{},"SystemProperties":{"connectionDeviceId":"901288002989997","connectionAuthMethod":"{\"scope\":\"device\",\"type\":\"sas\",\"issuer\":\"iothub\",\"acceptingIpFilterRule\":null}","connectionDeviceGenerationId":"637909662688020549","contentType":"application/json","contentEncoding":"utf-8","enqueuedTime":"2022-06-18T23:50:09.0960000Z"},"Body":{"imsi":901288002989997,"sequence":304,"uptime":1102291,"temperature":[{"value":25.1,"timestamp":1655592600000},{"value":25.1,"timestamp":1655592900000},{"value":25.08,"timestamp":1655593200000},{"value":25.08,"timestamp":1655593500000},{"value":25.06,"timestamp":1655593800000},{"value":25.06,"timestamp":1655594100000},{"value":25.05,"timestamp":1655594400000},{"value":25.05,"timestamp":1655594700000},{"value":25.04,"timestamp":1655595000000},{"value":25.03,"timestamp":1655595300000},{"value":25.03,"timestamp":1655595600000},{"value":25.01,"timestamp":1655595900000}],"humidity":[{"value":44,"timestamp":1655592600000},{"value":44,"timestamp":1655592900000},{"value":44,"timestamp":1655593200000},{"value":44,"timestamp":1655593500000},{"value":44,"timestamp":1655593800000},{"value":44,"timestamp":1655594100000},{"value":44,"timestamp":1655594400000},{"value":44,"timestamp":1655594700000},{"value":44,"timestamp":1655595000000},{"value":44,"timestamp":1655595300000},{"value":44,"timestamp":1655595600000},{"value":44,"timestamp":1655595900000}],"orientation":3,"discharged":0,"ecl":1,"signal_power":-79.6,"snr":4.9}}