{"EnqueuedTimeUtc":"2022-09-10T06:49:00.5280000Z","Properties":{},"SystemProperties":{"connectionDeviceId":"901288002989991","connectionAuthMethod":"{\"scope\":\"device\",\"type\":\"sas\",\"issuer\":\"iothub\",\"acceptingIpFilterRule\":null}","connectionDeviceGenerationId":"637909662877731942","contentType":"application/json","contentEncoding":"utf-8","enqueuedTime":"2022-09-10T06:49:00.5280000Z"},"Body":{"imsi":901288002989991,"sequence":2313,"uptime":8471381,"temperature":[{"value":18.03,"timestamp":1662788940000},{"value":18.02,"timestamp":1662789240000},{"value":18.05,"timestamp":1662789540000},{"value":18.02,"timestamp":1662789840000},{"value":18.12,"timestamp":1662790140000},{"value":18.03,"timestamp":1662790440000},{"value":18.05,"timestamp":1662790740000},{"value":18.07,"timestamp":1662791040000},{"value":18.04,"timestamp":1662791340000},{"value":18.13,"timestamp":1662791640000},{"value":18.02,"timestamp":1662791940000},{"value":18.14,"timestamp":1662792240000}],"humidity":[{"value":74,"timestamp":1662788940000},{"value":74,"timestamp":1662789240000},{"value":74,"timestamp":1662789540000},{"value":74,"timestamp":1662789840000},{"value":73,"timestamp":1662790140000},{"value":73,"timestamp":1662790440000},{"value":73,"timestamp":1662790740000},{"value":74,"timestamp":1662791040000},{"value":73,"timestamp":1662791340000},{"value":73,"timestamp":1662791640000},{"value":73,"timestamp":1662791940000},{"value":72,"timestamp":1662792240000}],"orientation":3,"discharged":0,"ecl":0,"signal_power":-89.3,"snr":7.3}}
{"EnqueuedTimeUtc":"2022-09-10T06:50:07.6230000Z","Properties":{},"SystemProperties":{"connectionDeviceId":"901288002989997","connectionAuthMethod":"{\"scope\":\"device\",\"type\":\"sas\",\"issuer\":\"iothub\",\"acceptingIpFilterRule\":null}","connectionDeviceGenerationId":"637909662688020549","contentType":"application/json","contentEncoding":"utf-8","enqueuedTime":"2022-09-10T06:50:07.6230000Z"},"Body":{"imsi":901288002989997,"sequence":2319,"uptime":8471370,"temperature":[{"value":19.24,"timestamp":1662789000000},{"value":19.22,"timestamp":1662789300000},{"value":19.7,"timestamp":1662789600000},{"value":19.6,"timestamp":1662789900000},{"value":20,"timestamp":1662790200000},{"value":19.55,"timestamp":1662790500000},{"value":19.37,"timestamp":1662790800000},{"value":19.26,"timestamp":1662791100000},{"value":19.1,"timestamp":1662791400000},{"value":19.45,"timestamp":1662791700000},{"value":19.51,"timestamp":1662792000000},{"value":19.83,"timestamp":1662792300000}],"humidity":[{"value":52,"timestamp":1662789000000},{"value":56,"timestamp":1662789300000},{"value":65,"timestamp":1662789600000},{"value":69,"timestamp":1662789900000},{"value":69,"timestamp":1662790200000},{"value":61,"timestamp":1662790500000},{"value":55,"timestamp":1662790800000},{"value":53,"timestamp":1662791100000},{"value":51,"timestamp":1662791400000},{"value":61,"timestamp":1662791700000},{"value":64,"timestamp":1662792000000},{"value":71,"timestamp":1662792300000}],"orientation":3,"discharged":0,"ecl":0,"signal_power":-92.1,"snr":8.4}}