{"EnqueuedTimeUtc":"2022-07-29T05:49:05.4940000Z","Properties":{},"SystemProperties":{"connectionDeviceId":"901288002989991","connectionAuthMethod":"{\"scope\":\"device\",\"type\":\"sas\",\"issuer\":\"iothub\",\"acceptingIpFilterRule\":null}","connectionDeviceGenerationId":"637909662877731942","contentType":"application/json","contentEncoding":"utf-8","enqueuedTime":"2022-07-29T05:49:05.4940000Z"},"Body":{"imsi":901288002989991,"sequence":1279,"uptime":4663306,"temperature":[{"value":23.53,"timestamp":1659070140000},{"value":23.54,"timestamp":1659070440000},{"value":23.55,"timestamp":1659070740000},{"value":23.55,"timestamp":1659071040000},{"value":23.51,"timestamp":1659071340000},{"value":23.52,"timestamp":1659071640000},{"value":23.52,"timestamp":1659071940000},{"value":23.53,"timestamp":1659072240000},{"value":23.55,"timestamp":1659072540000},{"value":23.57,"timestamp":1659072840000},{"value":23.59,"timestamp":1659073140000},{"value":23.6,"timestamp":1659073440000}],"humidity":[{"value":44,"timestamp":1659070140000},{"value":44,"timestamp":1659070440000},{"value":44,"timestamp":1659070740000},{"value":44,"timestamp":1659071040000},{"value":44,"timestamp":1659071340000},{"value":44,"timestamp":1659071640000},{"value":44,"timestamp":1659071940000},{"value":44,"timestamp":1659072240000},{"value":43,"timestamp":1659072540000},{"value":43,"timestamp":1659072840000},{"value":43,"timestamp":1659073140000},{"value":43,"timestamp":1659073440000}],"orientation":5,"discharged":0,"ecl":1,"signal_power":-88.5,"snr":0.5}}
{"EnqueuedTimeUtc":"2022-07-29T05:50:05.3850000Z","Properties":{},"SystemProperties":{"connectionDeviceId":"901288002989997","connectionAuthMethod":"{\"scope\":\"device\",\"type\":\"sas\",\"issuer\":\"iothub\",\"acceptingIpFilterRule\":null}","connectionDeviceGenerationId":"637909662688020549","contentType":"application/json","contentEncoding":"utf-8","enqueuedTime":"2022-07-29T05:50:05.3850000Z"},"Body":{"imsi":901288002989997,"sequence":1279,"uptime":4663334,"temperature":[{"value":24.38,"timestamp":1659070200000},{"value":24.32,"timestamp":1659070500000},{"value":24.38,"timestamp":1659070800000},{"value":24.37,"timestamp":1659071100000},{"value":24.27,"timestamp":1659071400000},{"value":24.48,"timestamp":1659071700000},{"value":24.51,"timestamp":1659072000000},{"value":24.64,"timestamp":1659072300000},{"value":24.7,"timestamp":1659072600000},{"value":24.79,"timestamp":1659072900000},{"value":24.68,"timestamp":1659073200000},{"value":24.55,"timestamp":1659073500000}],"humidity":[{"value":40,"timestamp":1659070200000},{"value":40,"timestamp":1659070500000},{"value":40,"timestamp":1659070800000},{"value":40,"timestamp":1659071100000},{"value":40,"timestamp":1659071400000},{"value":40,"timestamp":1659071700000},{"value":40,"timestamp":1659072000000},{"value":40,"timestamp":1659072300000},{"value":40,"timestamp":1659072600000},{"value":40,"timestamp":1659072900000},{"value":40,"timestamp":1659073200000},{"value":41,"timestamp":1659073500000}],"orientation":2,"discharged":0,"ecl":1,"signal_power":-78.9,"snr":2.2}}