{"EnqueuedTimeUtc":"2022-09-05T03:49:02.3110000Z","Properties":{},"SystemProperties":{"connectionDeviceId":"901288002989991","connectionAuthMethod":"{\"scope\":\"device\",\"type\":\"sas\",\"issuer\":\"iothub\",\"acceptingIpFilterRule\":null}","connectionDeviceGenerationId":"637909662877731942","contentType":"application/json","contentEncoding":"utf-8","enqueuedTime":"2022-09-05T03:49:02.3110000Z"},"Body":{"imsi":901288002989991,"sequence":2190,"uptime":8017954,"temperature":[{"value":18.09,"timestamp":1662346140000},{"value":18.26,"timestamp":1662346440000},{"value":18.11,"timestamp":1662346740000},{"value":18.22,"timestamp":1662347040000},{"value":18.24,"timestamp":1662347340000},{"value":18.13,"timestamp":1662347640000},{"value":18.21,"timestamp":1662347940000},{"value":18.1,"timestamp":1662348240000},{"value":18.15,"timestamp":1662348540000},{"value":18.19,"timestamp":1662348840000},{"value":18.1,"timestamp":1662349140000},{"value":18.14,"timestamp":1662349440000}],"humidity":[{"value":72,"timestamp":1662346140000},{"value":71,"timestamp":1662346440000},{"value":72,"timestamp":1662346740000},{"value":71,"timestamp":1662347040000},{"value":70,"timestamp":1662347340000},{"value":71,"timestamp":1662347640000},{"value":72,"timestamp":1662347940000},{"value":72,"timestamp":1662348240000},{"value":72,"timestamp":1662348540000},{"value":71,"timestamp":1662348840000},{"value":70,"timestamp":1662349140000},{"value":71,"timestamp":1662349440000}],"orientation":3,"discharged":0,"ecl":1,"signal_power":-91.9,"snr":2.6}}
{"EnqueuedTimeUtc":"2022-09-05T03:50:04.8800000Z","Properties":{},"SystemProperties":{"connectionDeviceId":"901288002989997","connectionAuthMethod":"{\"scope\":\"device\",\"type\":\"sas\",\"issuer\":\"iothub\",\"acceptingIpFilterRule\":null}","connectionDeviceGenerationId":"637909662688020549","contentType":"application/json","contentEncoding":"utf-8","enqueuedTime":"2022-09-05T03:50:04.8800000Z"},"Body":{"imsi":901288002989997,"sequence":2196,"uptime":8017942,"temperature":[{"value":19.18,"timestamp":1662346200000},{"value":19.29,"timestamp":1662346500000},{"value":19.23,"timestamp":1662346800000},{"value":19.24,"timestamp":1662347100000},{"value":19.22,"timestamp":1662347400000},{"value":19.19,"timestamp":1662347700000},{"value":19.29,"timestamp":1662348000000},{"value":19.18,"timestamp":1662348300000},{"value":19.27,"timestamp":1662348600000},{"value":19.17,"timestamp":1662348900000},{"value":19.24,"timestamp":1662349200000},{"value":19.25,"timestamp":1662349500000}],"humidity":[{"value":62,"timestamp":1662346200000},{"value":71,"timestamp":1662346500000},{"value":63,"timestamp":1662346800000},{"value":71,"timestamp":1662347100000},{"value":65,"timestamp":1662347400000},{"value":68,"timestamp":1662347700000},{"value":69,"timestamp":1662348000000},{"value":63,"timestamp":1662348300000},{"value":72,"timestamp":1662348600000},{"value":62,"timestamp":1662348900000},{"value":71,"timestamp":1662349200000},{"value":66,"timestamp":1662349500000}],"orientation":3,"discharged":0,"ecl":0,"signal_power":-93.3,"snr":8.1}}