{"EnqueuedTimeUtc":"2022-07-27T15:49:02.3420000Z","Properties":{},"SystemProperties":{"connectionDeviceId":"901288002989991","connectionAuthMethod":"{\"scope\":\"device\",\"type\":\"sas\",\"issuer\":\"iothub\",\"acceptingIpFilterRule\":null}","connectionDeviceGenerationId":"637909662877731942","contentType":"application/json","contentEncoding":"utf-8","enqueuedTime":"2022-07-27T15:49:02.3420000Z"},"Body":{"imsi":901288002989991,"sequence":1241,"uptime":4523223,"temperature":[{"value":24.1,"timestamp":1658933340000},{"value":24.38,"timestamp":1658933640000},{"value":24.33,"timestamp":1658933940000},{"value":24.33,"timestamp":1658934240000},{"value":24.51,"timestamp":1658934540000},{"value":24.59,"timestamp":1658934840000},{"value":24.58,"timestamp":1658935140000},{"value":24.55,"timestamp":1658935440000},{"value":24.59,"timestamp":1658935740000},{"value":24.64,"timestamp":1658936040000},{"value":24.67,"timestamp":1658936340000},{"value":24.68,"timestamp":1658936640000}],"humidity":[{"value":45,"timestamp":1658933340000},{"value":44,"timestamp":1658933640000},{"value":44,"timestamp":1658933940000},{"value":44,"timestamp":1658934240000},{"value":43,"timestamp":1658934540000},{"value":44,"timestamp":1658934840000},{"value":44,"timestamp":1658935140000},{"value":43,"timestamp":1658935440000},{"value":43,"timestamp":1658935740000},{"value":43,"timestamp":1658936040000},{"value":43,"timestamp":1658936340000},{"value":43,"timestamp":1658936640000}],"orientation":5,"discharged":0,"ecl":1,"signal_power":-86.1,"snr":0.7}}
{"EnqueuedTimeUtc":"2022-07-27T15:50:04.3640000Z","Properties":{},"SystemProperties":{"connectionDeviceId":"901288002989997","connectionAuthMethod":"{\"scope\":\"device\",\"type\":\"sas\",\"issuer\":\"iothub\",\"acceptingIpFilterRule\":null}","connectionDeviceGenerationId":"637909662688020549","contentType":"application/json","contentEncoding":"utf-8","enqueuedTime":"2022-07-27T15:50:04.3640000Z"},"Body":{"imsi":901288002989997,"sequence":1240,"uptime":4523251,"temperature":[{"value":25.01,"timestamp":1658933400000},{"value":25.16,"timestamp":1658933700000},{"value":25.08,"timestamp":1658934000000},{"value":24.96,"timestamp":1658934300000},{"value":25.04,"timestamp":1658934600000},{"value":25.12,"timestamp":1658934900000},{"value":24.88,"timestamp":1658935200000},{"value":24.81,"timestamp":1658935500000},{"value":24.78,"timestamp":1658935800000},{"value":24.66,"timestamp":1658936100000},{"value":24.7,"timestamp":1658936400000},{"value":24.92,"timestamp":1658936700000}],"humidity":[{"value":43,"timestamp":1658933400000},{"value":43,"timestamp":1658933700000},{"value":43,"timestamp":1658934000000},{"value":43,"timestamp":1658934300000},{"value":43,"timestamp":1658934600000},{"value":43,"timestamp":1658934900000},{"value":43,"timestamp":1658935200000},{"value":44,"timestamp":1658935500000},{"value":43,"timestamp":1658935800000},{"value":44,"timestamp":1658936100000},{"value":44,"timestamp":1658936400000},{"value":43,"timestamp":1658936700000}],"orientation":2,"discharged":0,"ecl":1,"signal_power":-80.7,"snr":-3}}