{"EnqueuedTimeUtc":"2022-07-23T17:48:57.4030000Z","Properties":{},"SystemProperties":{"connectionDeviceId":"901288002989991","connectionAuthMethod":"{\"scope\":\"device\",\"type\":\"sas\",\"issuer\":\"iothub\",\"acceptingIpFilterRule\":null}","connectionDeviceGenerationId":"637909662877731942","contentType":"application/json","contentEncoding":"utf-8","enqueuedTime":"2022-07-23T17:48:57.4030000Z"},"Body":{"imsi":901288002989991,"sequence":1146,"uptime":4176694,"temperature":[{"value":23.68,"timestamp":1658594940000},{"value":23.67,"timestamp":1658595240000},{"value":23.56,"timestamp":1658595540000},{"value":23.19,"timestamp":1658595840000},{"value":23.21,"timestamp":1658596140000},{"value":23.27,"timestamp":1658596440000},{"value":23.37,"timestamp":1658596740000},{"value":23.47,"timestamp":1658597040000},{"value":23.23,"timestamp":1658597340000},{"value":23.29,"timestamp":1658597640000},{"value":23.48,"timestamp":1658597940000},{"value":23.59,"timestamp":1658598240000}],"humidity":[{"value":55,"timestamp":1658594940000},{"value":55,"timestamp":1658595240000},{"value":54,"timestamp":1658595540000},{"value":54,"timestamp":1658595840000},{"value":55,"timestamp":1658596140000},{"value":56,"timestamp":1658596440000},{"value":55,"timestamp":1658596740000},{"value":54,"timestamp":1658597040000},{"value":54,"timestamp":1658597340000},{"value":54,"timestamp":1658597640000},{"value":54,"timestamp":1658597940000},{"value":54,"timestamp":1658598240000}],"orientation":5,"discharged":0,"ecl":1,"signal_power":-86.2,"snr":-0.8}}
{"EnqueuedTimeUtc":"2022-07-23T17:50:05.5360000Z","Properties":{},"SystemProperties":{"connectionDeviceId":"901288002989997","connectionAuthMethod":"{\"scope\":\"device\",\"type\":\"sas\",\"issuer\":\"iothub\",\"acceptingIpFilterRule\":null}","connectionDeviceGenerationId":"637909662688020549","contentType":"application/json","contentEncoding":"utf-8","enqueuedTime":"2022-07-23T17:50:05.5360000Z"},"Body":{"imsi":901288002989997,"sequence":1145,"uptime":4176731,"temperature":[{"value":23.6,"timestamp":1658595000000},{"value":23.4,"timestamp":1658595300000},{"value":23.38,"timestamp":1658595600000},{"value":23.5,"timestamp":1658595900000},{"value":23.6,"timestamp":1658596200000},{"value":23.51,"timestamp":1658596500000},{"value":23.31,"timestamp":1658596800000},{"value":23.22,"timestamp":1658597100000},{"value":23.24,"timestamp":1658597400000},{"value":23.32,"timestamp":1658597700000},{"value":23.2,"timestamp":1658598000000},{"value":23.12,"timestamp":1658598300000}],"humidity":[{"value":58,"timestamp":1658595000000},{"value":57,"timestamp":1658595300000},{"value":58,"timestamp":1658595600000},{"value":58,"timestamp":1658595900000},{"value":58,"timestamp":1658596200000},{"value":57,"timestamp":1658596500000},{"value":57,"timestamp":1658596800000},{"value":58,"timestamp":1658597100000},{"value":59,"timestamp":1658597400000},{"value":58,"timestamp":1658597700000},{"value":57,"timestamp":1658598000000},{"value":57,"timestamp":1658598300000}],"orientation":2,"discharged":0,"ecl":1,"signal_power":-73.7,"snr":6}}