{"EnqueuedTimeUtc":"2022-06-17T22:50:30.2120000Z","Properties":{},"SystemProperties":{"connectionDeviceId":"901288002989997","connectionAuthMethod":"{\"scope\":\"device\",\"type\":\"sas\",\"issuer\":\"iothub\",\"acceptingIpFilterRule\":null}","connectionDeviceGenerationId":"637909662688020549","contentType":"application/json","contentEncoding":"utf-8","enqueuedTime":"2022-06-17T22:50:30.2120000Z"},"Body":{"imsi":901288002989997,"sequence":279,"uptime":1010131,"temperature":[{"value":25.03,"timestamp":1655502600000},{"value":25.02,"timestamp":1655502900000},{"value":24.99,"timestamp":1655503200000},{"value":24.98,"timestamp":1655503500000},{"value":24.96,"timestamp":1655503800000},{"value":24.94,"timestamp":1655504100000},{"value":24.9,"timestamp":1655504400000},{"value":24.9,"timestamp":1655504700000},{"value":24.88,"timestamp":1655505000000},{"value":24.84,"timestamp":1655505300000},{"value":24.82,"timestamp":1655505600000},{"value":24.8,"timestamp":1655505900000}],"humidity":[{"value":41,"timestamp":1655502600000},{"value":41,"timestamp":1655502900000},{"value":41,"timestamp":1655503200000},{"value":41,"timestamp":1655503500000},{"value":41,"timestamp":1655503800000},{"value":41,"timestamp":1655504100000},{"value":41,"timestamp":1655504400000},{"value":40,"timestamp":1655504700000},{"value":40,"timestamp":1655505000000},{"value":40,"timestamp":1655505300000},{"value":40,"timestamp":1655505600000},{"value":40,"timestamp":1655505900000}],"orientation":3,"discharged":0,"ecl":1,"signal_power":-80.1,"snr":2.6}}