{"EnqueuedTimeUtc":"2022-07-19T03:49:01.1230000Z","Properties":{},"SystemProperties":{"connectionDeviceId":"901288002989991","connectionAuthMethod":"{\"scope\":\"device\",\"type\":\"sas\",\"issuer\":\"iothub\",\"acceptingIpFilterRule\":null}","connectionDeviceGenerationId":"637909662877731942","contentType":"application/json","contentEncoding":"utf-8","enqueuedTime":"2022-07-19T03:49:01.1230000Z"},"Body":{"imsi":901288002989991,"sequence":1036,"uptime":3771190,"temperature":[{"value":23.52,"timestamp":1658198940000},{"value":23.52,"timestamp":1658199240000},{"value":23.52,"timestamp":1658199540000},{"value":23.52,"timestamp":1658199840000},{"value":23.53,"timestamp":1658200140000},{"value":23.52,"timestamp":1658200440000},{"value":23.52,"timestamp":1658200740000},{"value":23.53,"timestamp":1658201040000},{"value":23.55,"timestamp":1658201340000},{"value":23.54,"timestamp":1658201640000},{"value":23.56,"timestamp":1658201940000},{"value":23.55,"timestamp":1658202240000}],"humidity":[{"value":42,"timestamp":1658198940000},{"value":42,"timestamp":1658199240000},{"value":42,"timestamp":1658199540000},{"value":42,"timestamp":1658199840000},{"value":42,"timestamp":1658200140000},{"value":42,"timestamp":1658200440000},{"value":42,"timestamp":1658200740000},{"value":42,"timestamp":1658201040000},{"value":42,"timestamp":1658201340000},{"value":42,"timestamp":1658201640000},{"value":42,"timestamp":1658201940000},{"value":42,"timestamp":1658202240000}],"orientation":3,"discharged":0,"ecl":1,"signal_power":-79.9,"snr":3.8}}
{"EnqueuedTimeUtc":"2022-07-19T03:50:06.5030000Z","Properties":{},"SystemProperties":{"connectionDeviceId":"901288002989997","connectionAuthMethod":"{\"scope\":\"device\",\"type\":\"sas\",\"issuer\":\"iothub\",\"acceptingIpFilterRule\":null}","connectionDeviceGenerationId":"637909662688020549","contentType":"application/json","contentEncoding":"utf-8","enqueuedTime":"2022-07-19T03:50:06.5030000Z"},"Body":{"imsi":901288002989997,"sequence":1033,"uptime":3771228,"temperature":[{"value":24.36,"timestamp":1658199000000},{"value":24.37,"timestamp":1658199300000},{"value":24.36,"timestamp":1658199600000},{"value":24.36,"timestamp":1658199900000},{"value":24.38,"timestamp":1658200200000},{"value":24.24,"timestamp":1658200500000},{"value":24.2,"timestamp":1658200800000},{"value":24.21,"timestamp":1658201100000},{"value":24.15,"timestamp":1658201400000},{"value":23.92,"timestamp":1658201700000},{"value":23.92,"timestamp":1658202000000},{"value":23.97,"timestamp":1658202300000}],"humidity":[{"value":40,"timestamp":1658199000000},{"value":40,"timestamp":1658199300000},{"value":40,"timestamp":1658199600000},{"value":40,"timestamp":1658199900000},{"value":40,"timestamp":1658200200000},{"value":40,"timestamp":1658200500000},{"value":41,"timestamp":1658200800000},{"value":41,"timestamp":1658201100000},{"value":41,"timestamp":1658201400000},{"value":41,"timestamp":1658201700000},{"value":41,"timestamp":1658202000000},{"value":41,"timestamp":1658202300000}],"orientation":2,"discharged":0,"ecl":1,"signal_power":-73.5,"snr":4.1}}