{"EnqueuedTimeUtc":"2022-07-13T03:50:09.3890000Z","Properties":{},"SystemProperties":{"connectionDeviceId":"901288002989997","connectionAuthMethod":"{\"scope\":\"device\",\"type\":\"sas\",\"issuer\":\"iothub\",\"acceptingIpFilterRule\":null}","connectionDeviceGenerationId":"637909662688020549","contentType":"application/json","contentEncoding":"utf-8","enqueuedTime":"2022-07-13T03:50:09.3890000Z"},"Body":{"imsi":901288002989997,"sequence":886,"uptime":3240392,"temperature":[{"value":23.45,"timestamp":1657680600000},{"value":23.44,"timestamp":1657680900000},{"value":23.43,"timestamp":1657681200000},{"value":23.42,"timestamp":1657681500000},{"value":23.42,"timestamp":1657681800000},{"value":23.41,"timestamp":1657682100000},{"value":23.41,"timestamp":1657682400000},{"value":23.4,"timestamp":1657682700000},{"value":23.4,"timestamp":1657683000000},{"value":23.41,"timestamp":1657683300000},{"value":23.41,"timestamp":1657683600000},{"value":23.42,"timestamp":1657683900000}],"humidity":[{"value":40,"timestamp":1657680600000},{"value":40,"timestamp":1657680900000},{"value":40,"timestamp":1657681200000},{"value":40,"timestamp":1657681500000},{"value":40,"timestamp":1657681800000},{"value":40,"timestamp":1657682100000},{"value":40,"timestamp":1657682400000},{"value":40,"timestamp":1657682700000},{"value":40,"timestamp":1657683000000},{"value":40,"timestamp":1657683300000},{"value":40,"timestamp":1657683600000},{"value":40,"timestamp":1657683900000}],"orientation":2,"discharged":0,"ecl":1,"signal_power":-75.8,"snr":0.5}}