{"EnqueuedTimeUtc":"2022-08-28T22:48:49.5190000Z","Properties":{},"SystemProperties":{"connectionDeviceId":"901288002989991","connectionAuthMethod":"{\"scope\":\"device\",\"type\":\"sas\",\"issuer\":\"iothub\",\"acceptingIpFilterRule\":null}","connectionDeviceGenerationId":"637909662877731942","contentType":"application/json","contentEncoding":"utf-8","enqueuedTime":"2022-08-28T22:48:49.5190000Z"},"Body":{"imsi":901288002989991,"sequence":2017,"uptime":7380190,"temperature":[{"value":18.11,"timestamp":1661723340000},{"value":17.92,"timestamp":1661723640000},{"value":18.06,"timestamp":1661723940000},{"value":18.03,"timestamp":1661724240000},{"value":17.94,"timestamp":1661724540000},{"value":18.1,"timestamp":1661724840000},{"value":17.9,"timestamp":1661725140000},{"value":18.03,"timestamp":1661725440000},{"value":18.02,"timestamp":1661725740000},{"value":17.96,"timestamp":1661726040000},{"value":18.1,"timestamp":1661726340000},{"value":17.93,"timestamp":1661726640000}],"humidity":[{"value":73,"timestamp":1661723340000},{"value":74,"timestamp":1661723640000},{"value":73,"timestamp":1661723940000},{"value":73,"timestamp":1661724240000},{"value":74,"timestamp":1661724540000},{"value":73,"timestamp":1661724840000},{"value":73,"timestamp":1661725140000},{"value":73,"timestamp":1661725440000},{"value":73,"timestamp":1661725740000},{"value":74,"timestamp":1661726040000},{"value":73,"timestamp":1661726340000},{"value":74,"timestamp":1661726640000}],"orientation":3,"discharged":0,"ecl":0,"signal_power":-88.8,"snr":4.5}}