{"EnqueuedTimeUtc":"2022-08-03T06:48:58.2140000Z","Properties":{},"SystemProperties":{"connectionDeviceId":"901288002989991","connectionAuthMethod":"{\"scope\":\"device\",\"type\":\"sas\",\"issuer\":\"iothub\",\"acceptingIpFilterRule\":null}","connectionDeviceGenerationId":"637909662877731942","contentType":"application/json","contentEncoding":"utf-8","enqueuedTime":"2022-08-03T06:48:58.2140000Z"},"Body":{"imsi":901288002989991,"sequence":1400,"uptime":5109361,"temperature":[{"value":23.63,"timestamp":1659505740000},{"value":23.7,"timestamp":1659506040000},{"value":23.7,"timestamp":1659506340000},{"value":23.63,"timestamp":1659506640000},{"value":23.73,"timestamp":1659506940000},{"value":23.79,"timestamp":1659507240000},{"value":23.86,"timestamp":1659507540000},{"value":23.89,"timestamp":1659507840000},{"value":23.8,"timestamp":1659508140000},{"value":23.81,"timestamp":1659508440000},{"value":23.88,"timestamp":1659508740000},{"value":24,"timestamp":1659509040000}],"humidity":[{"value":56,"timestamp":1659505740000},{"value":56,"timestamp":1659506040000},{"value":55,"timestamp":1659506340000},{"value":55,"timestamp":1659506640000},{"value":55,"timestamp":1659506940000},{"value":55,"timestamp":1659507240000},{"value":55,"timestamp":1659507540000},{"value":55,"timestamp":1659507840000},{"value":54,"timestamp":1659508140000},{"value":54,"timestamp":1659508440000},{"value":54,"timestamp":1659508740000},{"value":54,"timestamp":1659509040000}],"orientation":5,"discharged":0,"ecl":1,"signal_power":-84.4,"snr":2.7}}
{"EnqueuedTimeUtc":"2022-08-03T06:50:04.9730000Z","Properties":{},"SystemProperties":{"connectionDeviceId":"901288002989997","connectionAuthMethod":"{\"scope\":\"device\",\"type\":\"sas\",\"issuer\":\"iothub\",\"acceptingIpFilterRule\":null}","connectionDeviceGenerationId":"637909662688020549","contentType":"application/json","contentEncoding":"utf-8","enqueuedTime":"2022-08-03T06:50:04.9730000Z"},"Body":{"imsi":901288002989997,"sequence":1402,"uptime":5109386,"temperature":[{"value":24.34,"timestamp":1659505800000},{"value":24.31,"timestamp":1659506100000},{"value":24.24,"timestamp":1659506400000},{"value":24.12,"timestamp":1659506700000},{"value":24.07,"timestamp":1659507000000},{"value":24.1,"timestamp":1659507300000},{"value":24.11,"timestamp":1659507600000},{"value":24.22,"timestamp":1659507900000},{"value":24.3,"timestamp":1659508200000},{"value":24.45,"timestamp":1659508500000},{"value":24.59,"timestamp":1659508800000},{"value":24.59,"timestamp":1659509100000}],"humidity":[{"value":55,"timestamp":1659505800000},{"value":55,"timestamp":1659506100000},{"value":54,"timestamp":1659506400000},{"value":53,"timestamp":1659506700000},{"value":53,"timestamp":1659507000000},{"value":53,"timestamp":1659507300000},{"value":52,"timestamp":1659507600000},{"value":53,"timestamp":1659507900000},{"value":52,"timestamp":1659508200000},{"value":52,"timestamp":1659508500000},{"value":51,"timestamp":1659508800000},{"value":51,"timestamp":1659509100000}],"orientation":2,"discharged":0,"ecl":1,"signal_power":-77.6,"snr":2.7}}