{"EnqueuedTimeUtc":"2022-06-18T21:49:02.3920000Z","Properties":{},"SystemProperties":{"connectionDeviceId":"901288002989991","connectionAuthMethod":"{\"scope\":\"device\",\"type\":\"sas\",\"issuer\":\"iothub\",\"acceptingIpFilterRule\":null}","connectionDeviceGenerationId":"637909662877731942","contentType":"application/json","contentEncoding":"utf-8","enqueuedTime":"2022-06-18T21:49:02.3920000Z"},"Body":{"imsi":901288002989991,"sequence":308,"uptime":1094846,"temperature":[{"value":24.82,"timestamp":1655585340000},{"value":24.82,"timestamp":1655585640000},{"value":24.85,"timestamp":1655585940000},{"value":24.86,"timestamp":1655586240000},{"value":24.86,"timestamp":1655586540000},{"value":24.87,"timestamp":1655586840000},{"value":24.85,"timestamp":1655587140000},{"value":24.88,"timestamp":1655587440000},{"value":24.89,"timestamp":1655587740000},{"value":24.88,"timestamp":1655588040000},{"value":24.86,"timestamp":1655588340000},{"value":24.85,"timestamp":1655588640000}],"humidity":[{"value":44,"timestamp":1655585340000},{"value":44,"timestamp":1655585640000},{"value":44,"timestamp":1655585940000},{"value":44,"timestamp":1655586240000},{"value":44,"timestamp":1655586540000},{"value":44,"timestamp":1655586840000},{"value":44,"timestamp":1655587140000},{"value":44,"timestamp":1655587440000},{"value":44,"timestamp":1655587740000},{"value":44,"timestamp":1655588040000},{"value":44,"timestamp":1655588340000},{"value":44,"timestamp":1655588640000}],"orientation":3,"discharged":0,"ecl":1,"signal_power":-84.8,"snr":2.8}}
{"EnqueuedTimeUtc":"2022-06-18T21:50:08.2300000Z","Properties":{},"SystemProperties":{"connectionDeviceId":"901288002989997","connectionAuthMethod":"{\"scope\":\"device\",\"type\":\"sas\",\"issuer\":\"iothub\",\"acceptingIpFilterRule\":null}","connectionDeviceGenerationId":"637909662688020549","contentType":"application/json","contentEncoding":"utf-8","enqueuedTime":"2022-06-18T21:50:08.2300000Z"},"Body":{"imsi":901288002989997,"sequence":302,"uptime":1094918,"temperature":[{"value":25.22,"timestamp":1655585400000},{"value":25.22,"timestamp":1655585700000},{"value":25.22,"timestamp":1655586000000},{"value":25.22,"timestamp":1655586300000},{"value":25.22,"timestamp":1655586600000},{"value":25.23,"timestamp":1655586900000},{"value":25.22,"timestamp":1655587200000},{"value":25.21,"timestamp":1655587500000},{"value":25.21,"timestamp":1655587800000},{"value":25.19,"timestamp":1655588100000},{"value":25.19,"timestamp":1655588400000},{"value":25.18,"timestamp":1655588700000}],"humidity":[{"value":43,"timestamp":1655585400000},{"value":43,"timestamp":1655585700000},{"value":43,"timestamp":1655586000000},{"value":43,"timestamp":1655586300000},{"value":43,"timestamp":1655586600000},{"value":43,"timestamp":1655586900000},{"value":43,"timestamp":1655587200000},{"value":43,"timestamp":1655587500000},{"value":44,"timestamp":1655587800000},{"value":44,"timestamp":1655588100000},{"value":44,"timestamp":1655588400000},{"value":44,"timestamp":1655588700000}],"orientation":3,"discharged":0,"ecl":1,"signal_power":-79.9,"snr":6.7}}