{"EnqueuedTimeUtc":"2022-08-01T19:48:59.5680000Z","Properties":{},"SystemProperties":{"connectionDeviceId":"901288002989991","connectionAuthMethod":"{\"scope\":\"device\",\"type\":\"sas\",\"issuer\":\"iothub\",\"acceptingIpFilterRule\":null}","connectionDeviceGenerationId":"637909662877731942","contentType":"application/json","contentEncoding":"utf-8","enqueuedTime":"2022-08-01T19:48:59.5680000Z"},"Body":{"imsi":901288002989991,"sequence":1365,"uptime":4980337,"temperature":[{"value":24.09,"timestamp":1659379740000},{"value":24.05,"timestamp":1659380040000},{"value":24.04,"timestamp":1659380340000},{"value":24.13,"timestamp":1659380640000},{"value":24.19,"timestamp":1659380940000},{"value":24.2,"timestamp":1659381240000},{"value":24.23,"timestamp":1659381540000},{"value":24.23,"timestamp":1659381840000},{"value":24.24,"timestamp":1659382140000},{"value":24.26,"timestamp":1659382440000},{"value":24.26,"timestamp":1659382740000},{"value":24.28,"timestamp":1659383040000}],"humidity":[{"value":55,"timestamp":1659379740000},{"value":55,"timestamp":1659380040000},{"value":55,"timestamp":1659380340000},{"value":54,"timestamp":1659380640000},{"value":54,"timestamp":1659380940000},{"value":54,"timestamp":1659381240000},{"value":54,"timestamp":1659381540000},{"value":53,"timestamp":1659381840000},{"value":53,"timestamp":1659382140000},{"value":53,"timestamp":1659382440000},{"value":53,"timestamp":1659382740000},{"value":53,"timestamp":1659383040000}],"orientation":5,"discharged":0,"ecl":1,"signal_power":-82.4,"snr":5.3}}
{"EnqueuedTimeUtc":"2022-08-01T19:50:05.7480000Z","Properties":{},"SystemProperties":{"connectionDeviceId":"901288002989997","connectionAuthMethod":"{\"scope\":\"device\",\"type\":\"sas\",\"issuer\":\"iothub\",\"acceptingIpFilterRule\":null}","connectionDeviceGenerationId":"637909662688020549","contentType":"application/json","contentEncoding":"utf-8","enqueuedTime":"2022-08-01T19:50:05.7480000Z"},"Body":{"imsi":901288002989997,"sequence":1365,"uptime":4980364,"temperature":[{"value":24.73,"timestamp":1659379800000},{"value":24.76,"timestamp":1659380100000},{"value":24.78,"timestamp":1659380400000},{"value":24.79,"timestamp":1659380700000},{"value":24.79,"timestamp":1659381000000},{"value":24.83,"timestamp":1659381300000},{"value":24.83,"timestamp":1659381600000},{"value":24.85,"timestamp":1659381900000},{"value":24.86,"timestamp":1659382200000},{"value":24.88,"timestamp":1659382500000},{"value":24.91,"timestamp":1659382800000},{"value":24.91,"timestamp":1659383100000}],"humidity":[{"value":54,"timestamp":1659379800000},{"value":54,"timestamp":1659380100000},{"value":55,"timestamp":1659380400000},{"value":55,"timestamp":1659380700000},{"value":55,"timestamp":1659381000000},{"value":55,"timestamp":1659381300000},{"value":55,"timestamp":1659381600000},{"value":55,"timestamp":1659381900000},{"value":55,"timestamp":1659382200000},{"value":55,"timestamp":1659382500000},{"value":55,"timestamp":1659382800000},{"value":55,"timestamp":1659383100000}],"orientation":2,"discharged":0,"ecl":1,"signal_power":-74.9,"snr":4.1}}